masonite/inertia/__init__.py
masonite/inertia/helpers.py
masonite/inertia/config/inertia.py
masonite/inertia/core/Inertia.py
masonite/inertia/core/InertiaResponse.py
masonite/inertia/core/Lazy.py
masonite/inertia/core/__init__.py
masonite/inertia/middleware/InertiaMiddleware.py
masonite/inertia/providers/InertiaProvider.py
masonite/inertia/providers/__init__.py
masonite/inertia/testing/InertiaTestingResponse.py
masonite/inertia/testing/__init__.py
inertia_masonite-4.2.11.dist-info/LICENSE
inertia_masonite-4.2.11.dist-info/METADATA
inertia_masonite-4.2.11.dist-info/WHEEL
inertia_masonite-4.2.11.dist-info/top_level.txt
inertia_masonite-4.2.11.dist-info/RECORD
